verigen/__init__.py
verigen/common.py
verigen/verigen.py
verigen-0.0.1.dist-info/licenses/LICENSE
verigen-0.0.1.dist-info/METADATA
verigen-0.0.1.dist-info/WHEEL
verigen-0.0.1.dist-info/top_level.txt
verigen-0.0.1.dist-info/RECORD
